{"rank": "High", "setName": "Vespoid Beta", "pieces": [{"type": "head", "imgsrc": "/file/Monster-Hunter-World/vespoid_helm_beta%20(2)_male.png", "defense": "38", "slots": {"gem_level_1": 1, "gem_level_2": 0, "gem_level_3": 0}, "skills": [{"skillName": "Quick Sheath", "level": 1}], "resistances": {"fire": "-2", "water": "1", "thunder": "1", "ice": "1", "dragon": "2"}}, {"type": "chest", "imgsrc": "/file/Monster-Hunter-World/vespoid_mail_beta_male.png", "defense": "38", "slots": {"gem_level_1": 1, "gem_level_2": 0, "gem_level_3": 0}, "skills": [{"skillName": "Windproof", "level": 1}], "resistances": {"fire": "-2", "water": "1", "thunder": "1", "ice": "1", "dragon": "2"}}, {"type": "gloves", "imgsrc": "/file/Monster-Hunter-World/vespoid_vambraces_beta_male.png", "defense": "38", "slots": {"gem_level_1": 1, "gem_level_2": 0, "gem_level_3": 0}, "skills": [{"skillName": "Paralysis Attack", "level": 1}], "resistances": {"fire": "-2", "water": "1", "thunder": "1", "ice": "1", "dragon": "2"}}, {"type": "waist", "imgsrc": "/file/Monster-Hunter-World/vespoid_coil_beta_male.png", "defense": "38", "slots": {"gem_level_1": 1, "gem_level_2": 0, "gem_level_3": 0}, "skills": [{"skillName": "Paralysis Resistance", "level": 1}], "resistances": {"fire": "-2", "water": "1", "thunder": "1", "ice": "1", "dragon": "2"}}, {"type": "legs", "imgsrc": "/file/Monster-Hunter-World/vespoid_greaves_beta_male.png", "defense": "38", "slots": {"gem_level_1": 1, "gem_level_2": 0, "gem_level_3": 0}, "skills": [{"skillName": "Honey Hunter", "level": 1}], "resistances": {"fire": "-2", "water": "1", "thunder": "1", "ice": "1", "dragon": "2"}}]}